LICENSE
MANIFEST.in
README.md
requirements.pip
setup.py
il2ds_log_parser/__init__.py
il2ds_log_parser/constants.py
il2ds_log_parser/content_processor.py
il2ds_log_parser/event_types.py
il2ds_log_parser/parser.py
il2ds_log_parser/regex.py
il2ds_log_parser.egg-info/PKG-INFO
il2ds_log_parser.egg-info/SOURCES.txt
il2ds_log_parser.egg-info/dependency_links.txt
il2ds_log_parser.egg-info/requires.txt
il2ds_log_parser.egg-info/top_level.txt