Metadata-Version: 1.1
Name: il2ds-log-parser
Version: 0.10.1
Summary: Parser of IL-2 FB Dedicated Server events log.
Home-page: https://github.com/IL2HorusTeam/il2ds-log-parser
Author: Alexander Oblovatniy
Author-email: oblovatniy@gmail.com
License: BSD License
Platform: UNKNOWN
Classifier: Development Status :: 4 - Beta
Classifier: Intended Audience :: Developers
Classifier: License :: Free for non-commercial use
Classifier: Natural Language :: English
Classifier: Operating System :: OS Independent
Classifier: Programming Language :: Python :: 2.7
Classifier: Topic :: Software Development :: Libraries
